neovi/__init__.py
neovi/can.py
neovi/ecu.py
neovi/neodevice.py
neovi/neovi.py
neovi/spec.py
neovi/structures.py
pyneovi-1.0.dist-info/DESCRIPTION.rst
pyneovi-1.0.dist-info/METADATA
pyneovi-1.0.dist-info/RECORD
pyneovi-1.0.dist-info/WHEEL
pyneovi-1.0.dist-info/metadata.json
pyneovi-1.0.dist-info/top_level.txt
