Metadata-Version: 2.0
Name: pyneovi
Version: 1.0
Summary: A wrapper around the API provided by Intrepid Control Systems for communicating with their NeoVI range of devices
Home-page: http://kempj.co.uk/projects/pyneovi/
Author: John Kemp
Author-email: kemp@kempj.co.uk
License: MIT
Platform: UNKNOWN
Classifier: Intended Audience :: Developers
Classifier: License :: OSI Approved :: MIT License
Classifier: Operating System :: OS Independent
